MANIFEST.in
README.md
requirements.txt
setup.py
locationExtractor/__init__.py
locationExtractor/locationExtractor.py
locationExtractor/locations.db
locationExtractor/locations.py
locationExtractor.egg-info/PKG-INFO
locationExtractor.egg-info/SOURCES.txt
locationExtractor.egg-info/dependency_links.txt
locationExtractor.egg-info/top_level.txt