Metadata-Version: 1.0
Name: locationExtractor
Version: 0.1.2.3
Summary: Searches location info from source. Tokenizes source and finds appropriate country
Home-page: https://github.com/fatihsucu/locationExtractor
Author: Mustafa Atik
Author-email: muatik@gmail.com
License: MIT
Platform: any
